asari/__init__.py
asari/auth.py
asari/client.py
asari/consts.py
asari/exceptions.py
asari/py.typed
asari_api_client-1.0.0.dist-info/METADATA
asari_api_client-1.0.0.dist-info/WHEEL
asari_api_client-1.0.0.dist-info/licenses/LICENSE.md
asari_api_client-1.0.0.dist-info/RECORD
