Metadata-Version: 2.4
Name: asari-api-client
Version: 1.0.0
Summary: API client for Asari CRM
Author-email: Damian Wąsik <damianwasik98@gmail.com>
License-File: LICENSE.md
Requires-Python: >=3.12
Requires-Dist: requests>=2.32.3
